gaugid/__init__.py
gaugid/auth.py
gaugid/client.py
gaugid/connection.py
gaugid/logger.py
gaugid/signature.py
gaugid/storage.py
gaugid/types.py
gaugid/utils.py
gaugid/integrations/__init__.py
gaugid/integrations/adk.py
gaugid/integrations/agno.py
gaugid/integrations/anthropic.py
gaugid/integrations/langgraph.py
gaugid/integrations/llama_index.py
gaugid/integrations/openai.py
gaugid-0.1.0.dist-info/METADATA
gaugid-0.1.0.dist-info/WHEEL
gaugid-0.1.0.dist-info/licenses/LICENSE
gaugid-0.1.0.dist-info/RECORD
