Metadata-Version: 2.4
Name: gaugid
Version: 0.1.0
Summary: Python SDK for Gaugid (a2p-cloud) service integration
Project-URL: Homepage, https://gaugid.com
Project-URL: Documentation, https://docs.gaugid.com
Project-URL: Repository, https://github.com/alpibrusl/gaugid-sdk
Project-URL: Source (Python), https://github.com/alpibrusl/gaugid-sdk/tree/main/gaugid-sdk-python
Project-URL: Changelog, https://github.com/alpibrusl/gaugid-sdk/blob/main/CHANGELOG.md
Project-URL: Issues, https://github.com/alpibrusl/gaugid-sdk/issues
Author: Gaugid SDK Team
License: EUPL-1.2
License-File: LICENSE
Keywords: a2p,agent,ai,gaugid,oauth,profile,sdk
Classifier: Development Status :: 3 - Alpha
Classifier: Intended Audience :: Developers
Classifier: License :: OSI Approved :: European Union Public Licence 1.2 (EUPL 1.2)
Classifier: Operating System :: OS Independent
Classifier: Programming Language :: Python :: 3
Classifier: Programming Language :: Python :: 3.10
Classifier: Programming Language :: Python :: 3.11
Classifier: Programming Language :: Python :: 3.12
Classifier: Topic :: Software Development :: Libraries :: Python Modules
Classifier: Typing :: Typed
Requires-Python: >=3.10
Requires-Dist: a2p-sdk>=0.1.1
Requires-Dist: cryptography>=41.0.0
Requires-Dist: httpx>=0.25.0
Requires-Dist: pydantic>=2.0.0
Provides-Extra: adk
Requires-Dist: google-adk>=1.22.0; extra == 'adk'
Requires-Dist: python-genai>=1.57.0; extra == 'adk'
Provides-Extra: agno
Requires-Dist: agno>=2.3.26; extra == 'agno'
Provides-Extra: all
Requires-Dist: agno>=2.3.26; extra == 'all'
Requires-Dist: anthropic>=0.75.0; extra == 'all'
Requires-Dist: crewai-tools>=1.8.0; extra == 'all'
Requires-Dist: crewai>=1.8.0; extra == 'all'
Requires-Dist: google-adk>=1.22.0; extra == 'all'
Requires-Dist: langchain-core>=1.26.0; extra == 'all'
Requires-Dist: langgraph>=1.0.6; extra == 'all'
Requires-Dist: llama-index-core>=0.14.12; extra == 'all'
Requires-Dist: openai-agents>=1.0.0; extra == 'all'
Requires-Dist: python-genai>=1.57.0; extra == 'all'
Provides-Extra: anthropic
Requires-Dist: anthropic>=0.75.0; extra == 'anthropic'
Provides-Extra: crewai
Requires-Dist: crewai-tools>=1.8.0; extra == 'crewai'
Requires-Dist: crewai>=1.8.0; extra == 'crewai'
Provides-Extra: dev
Requires-Dist: black>=24.0.0; extra == 'dev'
Requires-Dist: mypy>=1.8.0; extra == 'dev'
Requires-Dist: pre-commit>=3.6.0; extra == 'dev'
Requires-Dist: pytest-asyncio>=0.23.0; extra == 'dev'
Requires-Dist: pytest-cov>=4.1.0; extra == 'dev'
Requires-Dist: pytest-mock>=3.12.0; extra == 'dev'
Requires-Dist: pytest>=8.0.0; extra == 'dev'
Requires-Dist: ruff>=0.1.0; extra == 'dev'
Requires-Dist: types-requests>=2.31.0; extra == 'dev'
Provides-Extra: langgraph
Requires-Dist: langchain-core>=1.26.0; extra == 'langgraph'
Requires-Dist: langgraph>=1.0.6; extra == 'langgraph'
Provides-Extra: llama-index
Requires-Dist: llama-index-core>=0.14.12; extra == 'llama-index'
Provides-Extra: openai
Requires-Dist: openai-agents>=1.0.0; extra == 'openai'
